allthekernels.py
allthekernels-1.2.0.data/data/share/jupyter/kernels/atk/kernel.json
allthekernels-1.2.0.dist-info/LICENSE
allthekernels-1.2.0.dist-info/METADATA
allthekernels-1.2.0.dist-info/WHEEL
allthekernels-1.2.0.dist-info/top_level.txt
allthekernels-1.2.0.dist-info/RECORD
