Metadata-Version: 2.1
Name: allthekernels
Version: 1.2.0
Summary: Multiplexing kernel for Jupyter
Home-page: https://github.com/minrk/allthekernels
Author: Min RK
Author-email: benjaminrk@gmail.com
License: MIT
Classifier: Development Status :: 3 - Alpha
Classifier: Intended Audience :: Developers
Classifier: License :: OSI Approved :: MIT License
Classifier: Programming Language :: Python :: 3
Requires-Python: >=3.5
License-File: LICENSE
Requires-Dist: ipykernel (>=6.0)
Requires-Dist: jupyter-client (>=5.0)
Requires-Dist: pyzmq (>=15.2)
Requires-Dist: tornado (>=5)
